{
  "mode": "ADDITIVE",
  "targets": [
    {
      "type": "aequivaleo:itemstack",
      "data": {
        "count": 1.0,
        "stack": "{id:\"elementsofpower:ruby_block\",Count:1b}"
      }
    },
    {
      "type": "aequivaleo:item",
      "data": {
        "count": 1.0,
        "item": "elementsofpower:ruby_block"
      }
    }
  ],
  "compounds": [
    {
      "amount": 19.0,
      "type": "elementsofpower:earth"
    },
    {
      "amount": 1.0,
      "type": "elementsofpower:fire"
    }
  ]
}